src/__init__.py
src/client.py
src/main.py
src/method.py
src/object.py
src/utils.py
shortvideo-1.0.6.dist-info/METADATA
shortvideo-1.0.6.dist-info/WHEEL
shortvideo-1.0.6.dist-info/entry_points.txt
shortvideo-1.0.6.dist-info/top_level.txt
shortvideo-1.0.6.dist-info/RECORD
